torchps/__init__.py
torchps/flat_phase_space_generator.py
torchps/utils.py
torchps-1.0.1.dist-info/LICENSE
torchps-1.0.1.dist-info/METADATA
torchps-1.0.1.dist-info/WHEEL
torchps-1.0.1.dist-info/top_level.txt
torchps-1.0.1.dist-info/RECORD
